remagic/__init__.py
remagic/main.py
remagic/main.pyi
remagic/pattern.py
remagic/py.typed
remagic/utils.py
remagic-0.0.4.dist-info/LICENSE
remagic-0.0.4.dist-info/METADATA
remagic-0.0.4.dist-info/WHEEL
remagic-0.0.4.dist-info/top_level.txt
remagic-0.0.4.dist-info/RECORD
