Metadata-Version: 2.1
Name: remagic
Version: 0.0.4
Summary: Work with RegEx with relative ease. Partly inspired by magic-regexp for Node
Home-page: https://github.com/ificiana/remagic
Author: Ificiana
Author-email: ificiana@gmail.com
License: MIT License
Keywords: remagic,regex
Platform: UNKNOWN
Classifier: License :: OSI Approved :: MIT License
Classifier: Programming Language :: Python
Classifier: Programming Language :: Python :: 3
Classifier: Programming Language :: Python :: 3.6
Classifier: Programming Language :: Python :: 3.7
Classifier: Programming Language :: Python :: 3.8
Classifier: Programming Language :: Python :: 3.9
Classifier: Programming Language :: Python :: 3.10
Classifier: Programming Language :: Python :: Implementation :: CPython
Classifier: Programming Language :: Python :: Implementation :: PyPy
